devtools_color_palette/__init__.py
devtools_color_palette-1.0.1.dist-info/METADATA
devtools_color_palette-1.0.1.dist-info/WHEEL
devtools_color_palette-1.0.1.dist-info/top_level.txt
devtools_color_palette-1.0.1.dist-info/RECORD
