Metadata-Version: 2.1
Name: devtools-color-palette
Version: 1.0.1
Summary: Color palette generator
Home-page: https://devtools.at/tools/color-palette
Author: DevTools.at
Author-email: hello@devtools.at
Project-URL: Homepage, https://devtools.at/tools/color-palette
Project-URL: Repository, https://github.com/devtools-at/color-palette
Classifier: Development Status :: 4 - Beta
Classifier: Intended Audience :: Developers
Classifier: License :: OSI Approved :: MIT License
Classifier: Programming Language :: Python :: 3
Requires-Python: >=3.8
